mocon/__init__.py
mocon-0.1.0.dist-info/LICENSE
mocon-0.1.0.dist-info/WHEEL
mocon-0.1.0.dist-info/METADATA
mocon-0.1.0.dist-info/RECORD
