Metadata-Version: 2.1
Name: mocon
Version: 0.1.0
Summary: Mocon is pluggable configuration management tool
Home-page: https://github.com/ischaojie/mocon
License: MIT
Author: ischaojie
Author-email: zhuzhezhe95@gmail.com
Requires-Python: >=3.7,<4.0
Classifier: License :: OSI Approved :: MIT License
Classifier: Programming Language :: Python :: 3
Classifier: Programming Language :: Python :: 3.7
Classifier: Programming Language :: Python :: 3.8
Classifier: Programming Language :: Python :: 3.9
Requires-Dist: WTForms (>=3.0.1,<4.0.0)
Requires-Dist: pydantic (>=1.9.0,<2.0.0)
Project-URL: Repository, https://github.com/ischaojie/mocon
